model_controller/__init__.py
model_controller/cli.py
model_controller/common.py
model_controller/download_artifact.py
model_controller/mlflow_base.py
model_controller/upload_artifact.py
model_controller-1.0.0.dist-info/METADATA
model_controller-1.0.0.dist-info/WHEEL
model_controller-1.0.0.dist-info/entry_points.txt
model_controller-1.0.0.dist-info/RECORD
