Metadata-Version: 2.4
Name: model_controller
Version: 1.0.0
Summary: AI-powered Git analysis tool using Gemini AI
Project-URL: Documentation, https://github.com/model_controller/model_controller#readme
Project-URL: Issues, https://github.com/model_controller/model_controller/issues
Author: Vumit Contributors
Classifier: Development Status :: 4 - Beta
Classifier: Environment :: Console
Classifier: Intended Audience :: Developers
Classifier: License :: OSI Approved :: MIT License
Classifier: Programming Language :: Python :: 3.9
Classifier: Topic :: Software Development :: Version Control :: Git
Requires-Python: >=3.9
Requires-Dist: click>=8.1.8
Requires-Dist: mlflow==2.13.0
